__init__.py
cloudformation.py
aws_ansible_sdk-0.0.2.dist-info/LICENSE
aws_ansible_sdk-0.0.2.dist-info/METADATA
aws_ansible_sdk-0.0.2.dist-info/WHEEL
aws_ansible_sdk-0.0.2.dist-info/top_level.txt
aws_ansible_sdk-0.0.2.dist-info/RECORD
