Metadata-Version: 2.1
Name: aws-ansible-sdk
Version: 0.0.2
Summary: Package to handle your cloud infrastructure
Author: Ash Bond
Classifier: Programming Language :: Python :: 3
Classifier: License :: OSI Approved :: MIT License
Classifier: Operating System :: OS Independent
Requires-Python: >=3.7
License-File: LICENSE
